spherical/dev/__init__.py
spherical/dev/cdk.py
spherical/dev/checkjson.py
spherical/dev/clean.py
spherical/dev/debugger.py
spherical/dev/dev.py
spherical/dev/devpi.py
spherical/dev/flake.py
spherical/dev/hooks.py
spherical/dev/isort.py
spherical/dev/log.py
spherical/dev/node.py
spherical/dev/pypi.py
spherical/dev/release.py
spherical/dev/tasks.py
spherical/dev/test.py
spherical/dev/utils.py
spherical/dev/wheel.py
spherical/dev/configs/pre-commit-config.yaml
spherical_dev-0.3.5.dist-info/LICENSE
spherical_dev-0.3.5.dist-info/METADATA
spherical_dev-0.3.5.dist-info/WHEEL
spherical_dev-0.3.5.dist-info/top_level.txt
spherical_dev-0.3.5.dist-info/RECORD
